{
  "problem_id": "S3_초등_3_008911",
  "view_box": {
    "width": 960.0,
    "height": 420.0,
    "background": "#FFFFFF"
  },
  "elements": [
    {
      "id": "slot.table_outer.rect",
      "type": "rect",
      "attributes": {
        "x": 140.0,
        "y": 140.0,
        "width": 690.0,
        "height": 80.0,
        "fill": "#ffffff",
        "stroke": "#111111",
        "stroke-width": 1.5
      },
      "source_ref": "slot.table_outer",
      "refs": {
        "layout_slot_id": "slot.table_outer"
      }
    },
    {
      "id": "slot.q1.text",
      "type": "text",
      "attributes": {
        "x": 14.0,
        "y": 24.0,
        "fill": "#111111",
        "font-family": "Noto Sans KR, sans-serif",
        "font-size": 28
      },
      "source_ref": "slot.q1",
      "refs": {
        "layout_slot_id": "slot.q1"
      },
      "text": "□ 77. 정국이네 반 학생들이 생일에 받고 싶은 선물을 사주하여 표로 나타냈습니다.\n가장 많은 학생들이 받고 싶은 선물을 선택하세요."
    },
    {
      "id": "slot.table_title.text",
      "type": "text",
      "attributes": {
        "x": 260.0,
        "y": 108.0,
        "fill": "#111111",
        "font-family": "Noto Sans KR, sans-serif",
        "font-size": 28
      },
      "source_ref": "slot.table_title",
      "refs": {
        "layout_slot_id": "slot.table_title"
      },
      "text": "생일에 받고 싶은 선물별 학생 수"
    },
    {
      "id": "slot.h1.text",
      "type": "text",
      "attributes": {
        "x": 162.0,
        "y": 169.0,
        "fill": "#111111",
        "font-family": "Noto Sans KR, sans-serif",
        "font-size": 28
      },
      "source_ref": "slot.h1",
      "refs": {
        "layout_slot_id": "slot.h1"
      },
      "text": "선물    책    휴대전화    게임기    옷    합계"
    },
    {
      "id": "slot.h2.text",
      "type": "text",
      "attributes": {
        "x": 160.0,
        "y": 206.0,
        "fill": "#111111",
        "font-family": "Noto Sans KR, sans-serif",
        "font-size": 28
      },
      "source_ref": "slot.h2",
      "refs": {
        "layout_slot_id": "slot.h2"
      },
      "text": "학생 수(명)    6    12    8    4    30"
    },
    {
      "id": "slot.view.text",
      "type": "text",
      "attributes": {
        "x": 610.0,
        "y": 266.0,
        "fill": "#111111",
        "font-family": "Noto Sans KR, sans-serif",
        "font-size": 28
      },
      "source_ref": "slot.view",
      "refs": {
        "layout_slot_id": "slot.view"
      },
      "text": "( 책 , 휴대전화 , 게임기 , 옷 )"
    }
  ],
  "contract_version": "modu_math.renderer.v2"
}
