{
  "problem_id": "S3_초등_3_008646",
  "view_box": {
    "width": 944.0,
    "height": 654.0,
    "background": "#FFFFFF"
  },
  "elements": [
    {
      "id": "slot.qnum.text",
      "type": "text",
      "attributes": {
        "x": 14.0,
        "y": 28.0,
        "max_width": 816.0,
        "fill": "#111111",
        "font-family": "Noto Sans KR, sans-serif",
        "font-size": 28
      },
      "source_ref": "slot.qnum",
      "refs": {
        "layout_slot_id": "slot.qnum"
      },
      "text": "18."
    },
    {
      "id": "slot.stem.text",
      "type": "text",
      "attributes": {
        "x": 68.0,
        "y": 28.0,
        "max_width": 816.0,
        "fill": "#111111",
        "font-family": "Noto Sans KR, sans-serif",
        "font-size": 28
      },
      "source_ref": "slot.stem",
      "refs": {
        "layout_slot_id": "slot.stem"
      },
      "text": "원 모양의 종이를 접어 위의 성질을 알아보고 알맞은 말을 선택하세요."
    },
    {
      "id": "slot.bubble.text",
      "type": "text",
      "attributes": {
        "x": 318.0,
        "y": 74.0,
        "max_width": 816.0,
        "fill": "#111111",
        "font-family": "Noto Sans KR, sans-serif",
        "font-size": 26
      },
      "source_ref": "slot.bubble",
      "refs": {
        "layout_slot_id": "slot.bubble"
      },
      "text": "원 모양의 종이를 둘로 똑같이 나누어지도록\n접었다가 펼친 다음 다른 방향으로 둘로 똑같이\n나누어지도록 접었다가 펼쳤어."
    },
    {
      "id": "slot.bubble.text1.text",
      "type": "text",
      "attributes": {
        "x": 0.0,
        "y": 0.0,
        "max_width": 816.0,
        "fill": "#111111",
        "font-family": "Noto Sans KR, sans-serif",
        "font-size": 28
      },
      "source_ref": "slot.bubble.text1",
      "refs": {
        "layout_slot_id": "slot.bubble.text1"
      },
      "text": ""
    },
    {
      "id": "slot.bubble.text2.text",
      "type": "text",
      "attributes": {
        "x": 0.0,
        "y": 0.0,
        "max_width": 816.0,
        "fill": "#111111",
        "font-family": "Noto Sans KR, sans-serif",
        "font-size": 28
      },
      "source_ref": "slot.bubble.text2",
      "refs": {
        "layout_slot_id": "slot.bubble.text2"
      },
      "text": ""
    },
    {
      "id": "slot.bubble.text3.text",
      "type": "text",
      "attributes": {
        "x": 0.0,
        "y": 0.0,
        "max_width": 816.0,
        "fill": "#111111",
        "font-family": "Noto Sans KR, sans-serif",
        "font-size": 28
      },
      "source_ref": "slot.bubble.text3",
      "refs": {
        "layout_slot_id": "slot.bubble.text3"
      },
      "text": ""
    },
    {
      "id": "slot.circle1.circle",
      "type": "circle",
      "attributes": {
        "cx": 88.0,
        "cy": 304.0,
        "r": 58.0,
        "stroke": "#111111",
        "stroke-width": 2.0,
        "fill": "#DFF2F0"
      },
      "source_ref": "slot.circle1",
      "refs": {
        "layout_slot_id": "slot.circle1"
      }
    },
    {
      "id": "slot.fold1.path",
      "type": "path",
      "attributes": {
        "d": "M 262.0 306.0 C 224.0 306.0, 210.0 306.0, 208.0 306.0 C 210.0 338.0, 232.0 357.0, 262.0 357.0",
        "stroke": "#111111",
        "stroke-width": 2.0,
        "fill": "none"
      },
      "source_ref": "slot.fold1",
      "refs": {
        "layout_slot_id": "slot.fold1"
      }
    },
    {
      "id": "slot.circle2.circle",
      "type": "circle",
      "attributes": {
        "cx": 518.0,
        "cy": 304.0,
        "r": 58.0,
        "stroke": "#111111",
        "stroke-width": 2.0,
        "fill": "#DFF2F0"
      },
      "source_ref": "slot.circle2",
      "refs": {
        "layout_slot_id": "slot.circle2"
      }
    },
    {
      "id": "slot.fold2.path",
      "type": "path",
      "attributes": {
        "d": "M 681.0 302.0 C 662.0 269.0, 656.0 248.0, 662.0 244.0 C 683.0 256.0, 702.0 286.0, 725.0 340.0 C 706.0 344.0, 692.0 342.0, 681.0 302.0",
        "stroke": "#111111",
        "stroke-width": 2.0,
        "fill": "none"
      },
      "source_ref": "slot.fold2",
      "refs": {
        "layout_slot_id": "slot.fold2"
      }
    },
    {
      "id": "slot.circle3.circle",
      "type": "circle",
      "attributes": {
        "cx": 878.0,
        "cy": 304.0,
        "r": 58.0,
        "stroke": "#111111",
        "stroke-width": 2.0,
        "fill": "#DFF2F0"
      },
      "source_ref": "slot.circle3",
      "refs": {
        "layout_slot_id": "slot.circle3"
      }
    },
    {
      "id": "slot.fold3.path",
      "type": "path",
      "attributes": {
        "d": "M 872.0 305.0 C 840.0 281.0, 828.0 258.0, 826.0 246.0 C 846.0 242.0, 866.0 247.0, 878.0 304.0",
        "stroke": "#111111",
        "stroke-width": 2.0,
        "fill": "none"
      },
      "source_ref": "slot.fold3",
      "refs": {
        "layout_slot_id": "slot.fold3"
      }
    },
    {
      "id": "slot.circle4.circle",
      "type": "circle",
      "attributes": {
        "cx": 878.0,
        "cy": 304.0,
        "r": 58.0,
        "stroke": "#111111",
        "stroke-width": 2.0,
        "fill": "#DFF2F0"
      },
      "source_ref": "slot.circle4",
      "refs": {
        "layout_slot_id": "slot.circle4"
      }
    },
    {
      "id": "slot.pinkdot.circle",
      "type": "circle",
      "attributes": {
        "cx": 866.0,
        "cy": 304.0,
        "r": 3.5,
        "stroke": "#111111",
        "stroke-width": 2.0,
        "fill": "#E11A86"
      },
      "source_ref": "slot.pinkdot",
      "refs": {
        "layout_slot_id": "slot.pinkdot"
      }
    },
    {
      "id": "slot.arrow1.line",
      "type": "line",
      "attributes": {
        "x1": 180.0,
        "y1": 304.0,
        "x2": 214.0,
        "y2": 304.0,
        "stroke": "#9A9A9A",
        "stroke-width": 2.0
      },
      "source_ref": "slot.arrow1",
      "refs": {
        "layout_slot_id": "slot.arrow1"
      }
    },
    {
      "id": "slot.arrow2.line",
      "type": "line",
      "attributes": {
        "x1": 392.0,
        "y1": 304.0,
        "x2": 426.0,
        "y2": 304.0,
        "stroke": "#9A9A9A",
        "stroke-width": 2.0
      },
      "source_ref": "slot.arrow2",
      "refs": {
        "layout_slot_id": "slot.arrow2"
      }
    },
    {
      "id": "slot.arrow3.line",
      "type": "line",
      "attributes": {
        "x1": 608.0,
        "y1": 304.0,
        "x2": 642.0,
        "y2": 304.0,
        "stroke": "#9A9A9A",
        "stroke-width": 2.0
      },
      "source_ref": "slot.arrow3",
      "refs": {
        "layout_slot_id": "slot.arrow3"
      }
    },
    {
      "id": "slot.arrow4.line",
      "type": "line",
      "attributes": {
        "x1": 790.0,
        "y1": 304.0,
        "x2": 824.0,
        "y2": 304.0,
        "stroke": "#9A9A9A",
        "stroke-width": 2.0
      },
      "source_ref": "slot.arrow4",
      "refs": {
        "layout_slot_id": "slot.arrow4"
      }
    },
    {
      "id": "slot.arrow5.line",
      "type": "line",
      "attributes": {
        "x1": 512.0,
        "y1": 230.0,
        "x2": 528.0,
        "y2": 210.0,
        "stroke": "#2AAE96",
        "stroke-width": 2.0
      },
      "source_ref": "slot.arrow5",
      "refs": {
        "layout_slot_id": "slot.arrow5"
      }
    },
    {
      "id": "slot.arrow6.line",
      "type": "line",
      "attributes": {
        "x1": 878.0,
        "y1": 304.0,
        "x2": 878.0,
        "y2": 248.0,
        "stroke": "#67C5E2",
        "stroke-width": 2.0
      },
      "source_ref": "slot.arrow6",
      "refs": {
        "layout_slot_id": "slot.arrow6"
      }
    },
    {
      "id": "slot.arrow7.line",
      "type": "line",
      "attributes": {
        "x1": 734.0,
        "y1": 304.0,
        "x2": 768.0,
        "y2": 304.0,
        "stroke": "#9A9A9A",
        "stroke-width": 2.0
      },
      "source_ref": "slot.arrow7",
      "refs": {
        "layout_slot_id": "slot.arrow7"
      }
    },
    {
      "id": "slot.green1.line",
      "type": "line",
      "attributes": {
        "x1": 835.0,
        "y1": 236.0,
        "x2": 900.0,
        "y2": 236.0,
        "stroke": "#1E9B53",
        "stroke-width": 2.0
      },
      "source_ref": "slot.green1",
      "refs": {
        "layout_slot_id": "slot.green1"
      }
    },
    {
      "id": "slot.green2.text",
      "type": "text",
      "attributes": {
        "x": 540.0,
        "y": 241.0,
        "max_width": 816.0,
        "fill": "#111111",
        "font-family": "Noto Sans KR, sans-serif",
        "font-size": 24
      },
      "source_ref": "slot.green2",
      "refs": {
        "layout_slot_id": "slot.green2"
      },
      "text": "접힌 선의 윗부분과 아랫부분이 똑같아요."
    },
    {
      "id": "slot.pinkbox.rect",
      "type": "rect",
      "attributes": {
        "x": 98.0,
        "y": 426.0,
        "width": 734.0,
        "height": 116.0,
        "fill": "#F9E0DA",
        "stroke": "#111111",
        "stroke-width": 1.5
      },
      "source_ref": "slot.pinkbox",
      "refs": {
        "layout_slot_id": "slot.pinkbox"
      }
    }
  ],
  "contract_version": "modu_math.renderer.v2"
}
