{
  "problem_id": "S3_초등_3_008888",
  "view_box": {
    "width": 960.0,
    "height": 720.0,
    "background": "#FFFFFF"
  },
  "elements": [
    {
      "id": "slot.table.frame.rect",
      "type": "rect",
      "attributes": {
        "x": 184.0,
        "y": 116.0,
        "width": 452.0,
        "height": 342.0,
        "fill": "#ffffff",
        "stroke": "#111111",
        "stroke-width": 1.5
      },
      "source_ref": "slot.table.frame",
      "refs": {
        "layout_slot_id": "slot.table.frame"
      }
    },
    {
      "id": "slot.q_num.text",
      "type": "text",
      "attributes": {
        "x": 16.0,
        "y": 34.0,
        "fill": "#111111",
        "font-family": "Noto Sans KR, sans-serif",
        "font-size": 28
      },
      "source_ref": "slot.q_num",
      "refs": {
        "layout_slot_id": "slot.q_num"
      },
      "text": "52."
    },
    {
      "id": "slot.q1.text",
      "type": "text",
      "attributes": {
        "x": 56.0,
        "y": 34.0,
        "fill": "#111111",
        "font-family": "Noto Sans KR, sans-serif",
        "font-size": 28
      },
      "source_ref": "slot.q1",
      "refs": {
        "layout_slot_id": "slot.q1"
      },
      "text": "지아가 요일별로 도서관을 이용한 학생 수를 그림으로 나타내어 그래프를 만들"
    },
    {
      "id": "slot.q2.text",
      "type": "text",
      "attributes": {
        "x": 40.0,
        "y": 66.0,
        "fill": "#111111",
        "font-family": "Noto Sans KR, sans-serif",
        "font-size": 28
      },
      "source_ref": "slot.q2",
      "refs": {
        "layout_slot_id": "slot.q2"
      },
      "text": "었습니다. 그래프를 보고 알맞은 말을 선택하세요."
    },
    {
      "id": "slot.title.text",
      "type": "text",
      "attributes": {
        "x": 282.0,
        "y": 106.0,
        "fill": "#111111",
        "font-family": "Noto Sans KR, sans-serif",
        "font-size": 28
      },
      "source_ref": "slot.title",
      "refs": {
        "layout_slot_id": "slot.title"
      },
      "text": "도서관을 이용한 학생 수"
    },
    {
      "id": "slot.table.head1.text",
      "type": "text",
      "attributes": {
        "x": 213.0,
        "y": 146.0,
        "fill": "#111111",
        "font-family": "Noto Sans KR, sans-serif",
        "font-size": 28
      },
      "source_ref": "slot.table.head1",
      "refs": {
        "layout_slot_id": "slot.table.head1"
      },
      "text": "요일"
    },
    {
      "id": "slot.table.head2.text",
      "type": "text",
      "attributes": {
        "x": 423.0,
        "y": 146.0,
        "fill": "#111111",
        "font-family": "Noto Sans KR, sans-serif",
        "font-size": 28
      },
      "source_ref": "slot.table.head2",
      "refs": {
        "layout_slot_id": "slot.table.head2"
      },
      "text": "학생 수"
    },
    {
      "id": "slot.table.row1.label.text",
      "type": "text",
      "attributes": {
        "x": 206.0,
        "y": 198.0,
        "fill": "#111111",
        "font-family": "Noto Sans KR, sans-serif",
        "font-size": 28
      },
      "source_ref": "slot.table.row1.label",
      "refs": {
        "layout_slot_id": "slot.table.row1.label"
      },
      "text": "월요일"
    },
    {
      "id": "slot.table.row2.label.text",
      "type": "text",
      "attributes": {
        "x": 206.0,
        "y": 260.0,
        "fill": "#111111",
        "font-family": "Noto Sans KR, sans-serif",
        "font-size": 28
      },
      "source_ref": "slot.table.row2.label",
      "refs": {
        "layout_slot_id": "slot.table.row2.label"
      },
      "text": "화요일"
    },
    {
      "id": "slot.table.row3.label.text",
      "type": "text",
      "attributes": {
        "x": 206.0,
        "y": 322.0,
        "fill": "#111111",
        "font-family": "Noto Sans KR, sans-serif",
        "font-size": 28
      },
      "source_ref": "slot.table.row3.label",
      "refs": {
        "layout_slot_id": "slot.table.row3.label"
      },
      "text": "수요일"
    },
    {
      "id": "slot.table.row4.label.text",
      "type": "text",
      "attributes": {
        "x": 206.0,
        "y": 384.0,
        "fill": "#111111",
        "font-family": "Noto Sans KR, sans-serif",
        "font-size": 28
      },
      "source_ref": "slot.table.row4.label",
      "refs": {
        "layout_slot_id": "slot.table.row4.label"
      },
      "text": "목요일"
    },
    {
      "id": "slot.table.row5.label.text",
      "type": "text",
      "attributes": {
        "x": 206.0,
        "y": 446.0,
        "fill": "#111111",
        "font-family": "Noto Sans KR, sans-serif",
        "font-size": 28
      },
      "source_ref": "slot.table.row5.label",
      "refs": {
        "layout_slot_id": "slot.table.row5.label"
      },
      "text": "금요일"
    },
    {
      "id": "slot.legend.big.text",
      "type": "text",
      "attributes": {
        "x": 718.0,
        "y": 374.0,
        "fill": "#111111",
        "font-family": "Noto Sans KR, sans-serif",
        "font-size": 28
      },
      "source_ref": "slot.legend.big",
      "refs": {
        "layout_slot_id": "slot.legend.big"
      },
      "text": "10명"
    },
    {
      "id": "slot.legend.small.text",
      "type": "text",
      "attributes": {
        "x": 718.0,
        "y": 450.0,
        "fill": "#111111",
        "font-family": "Noto Sans KR, sans-serif",
        "font-size": 28
      },
      "source_ref": "slot.legend.small",
      "refs": {
        "layout_slot_id": "slot.legend.small"
      },
      "text": "1명"
    },
    {
      "id": "slot.question.text",
      "type": "text",
      "attributes": {
        "x": 222.0,
        "y": 504.0,
        "fill": "#111111",
        "font-family": "Noto Sans KR, sans-serif",
        "font-size": 28
      },
      "source_ref": "slot.question",
      "refs": {
        "layout_slot_id": "slot.question"
      },
      "text": "도서관을 이용한 학생 수가 가장 많은 요일은"
    },
    {
      "id": "slot.choice.text",
      "type": "text",
      "attributes": {
        "x": 130.0,
        "y": 538.0,
        "fill": "#111111",
        "font-family": "Noto Sans KR, sans-serif",
        "font-size": 28
      },
      "source_ref": "slot.choice",
      "refs": {
        "layout_slot_id": "slot.choice"
      },
      "text": "( 월요일 , 화요일 , 수요일 , 목요일 , 금요일 )입니다."
    }
  ],
  "contract_version": "modu_math.renderer.v2"
}
