{
  "problem_id": "3rd_shape2d_0010",
  "view_box": {
    "width": 400.0,
    "height": 210.0,
    "background": "#F6F6F6"
  },
  "elements": [
    {
      "id": "bg",
      "type": "rect",
      "attributes": {
        "fill": "#F4F4F4",
        "stroke": "none",
        "stroke-width": 0,
        "x": 0.0,
        "y": 0.0,
        "width": 400,
        "height": 210
      }
    },
    {
      "id": "i1",
      "type": "text",
      "attributes": {
        "x": 4.0,
        "y": 34.0,
        "text-anchor": "start",
        "fill": "#222222",
        "font-family": "Malgun Gothic",
        "font-size": 17,
        "font-weight": "normal"
      },
      "text": "다음 도형에서 찾을 수 있는 크고 작은"
    },
    {
      "id": "i2",
      "type": "text",
      "attributes": {
        "x": 4.0,
        "y": 64.0,
        "text-anchor": "start",
        "fill": "#222222",
        "font-family": "Malgun Gothic",
        "font-size": 17,
        "font-weight": "normal"
      },
      "text": "직사각형은 모두 몇 개인지 구하세요."
    },
    {
      "id": "outer",
      "type": "rect",
      "attributes": {
        "fill": "none",
        "stroke": "#4A4A4A",
        "stroke-width": 2.0,
        "x": 148.0,
        "y": 104.0,
        "width": 126,
        "height": 96
      }
    },
    {
      "id": "v1",
      "type": "line",
      "attributes": {
        "stroke": "#4A4A4A",
        "stroke-width": 2.0,
        "x1": 190.0,
        "y1": 104.0,
        "x2": 190.0,
        "y2": 200.0
      }
    },
    {
      "id": "v2",
      "type": "line",
      "attributes": {
        "stroke": "#4A4A4A",
        "stroke-width": 2.0,
        "x1": 224.0,
        "y1": 104.0,
        "x2": 224.0,
        "y2": 200.0
      }
    },
    {
      "id": "h1",
      "type": "line",
      "attributes": {
        "stroke": "#4A4A4A",
        "stroke-width": 2.0,
        "x1": 148.0,
        "y1": 152.0,
        "x2": 224.0,
        "y2": 152.0
      }
    },
    {
      "id": "answer_value",
      "type": "rect",
      "attributes": {
        "fill": "none",
        "stroke": "none",
        "stroke-width": 0,
        "x": 336.0,
        "y": 176.0,
        "width": 56,
        "height": 28
      }
    }
  ]
}