{
  "schema_version": "modu_math.semantic.v3",
  "render_contract_version": "modu_math.render.v1",
  "problem_id": "0014",
  "problem_type": "mixed_fraction_division_range_count",
  "title": "대분수 나눗셈의 몫 범위",
  "metadata": {
    "source": {
      "input_type": "python_dsl",
      "generator": "modu_semantic"
    },
    "warnings": []
  },
  "domain": {
    "cards": [
      3,
      5,
      7,
      9
    ],
    "instruction_lines": [
      "숫자 카드",
      "를 모두 한 번씩만 사용하여",
      "다음과 같이 (대분수) ÷ (자연수)를 만들려고 합니다.",
      "만들 수 있는 값 중 몫이 가장 작을 때의 몫과 몫이",
      "가장 클 때의 몫 사이에 있는 자연수는 모두 몇 개인가요?"
    ],
    "answer_value": 3
  },
  "render": {
    "canvas": {
      "width": 980.0,
      "height": 493.0,
      "background": "#F6F6F6"
    },
    "elements": [
      {
        "id": "bg",
        "semantic_role": "background",
        "z_index": 0,
        "anchor": "start",
        "alignment": "left",
        "stroke": "none",
        "stroke_width": 0,
        "fill": "#F6F6F6",
        "font_family": "Malgun Gothic",
        "font_weight": "normal",
        "type": "rect",
        "x": 0.0,
        "y": 0.0,
        "width": 980,
        "height": 493
      },
      {
        "id": "l1a",
        "semantic_role": "instruction",
        "z_index": 0,
        "anchor": "start",
        "alignment": "left",
        "fill": "#222222",
        "font_family": "Malgun Gothic",
        "font_size": 34,
        "font_weight": "normal",
        "type": "text",
        "text": "숫자 카드",
        "x": 21.45,
        "y": 56.56
      },
      {
        "id": "card_1",
        "semantic_role": "card",
        "z_index": 0,
        "anchor": "start",
        "alignment": "left",
        "stroke": "#000000",
        "stroke_width": 1,
        "fill": "#BDBDBD",
        "font_family": "Malgun Gothic",
        "font_weight": "normal",
        "type": "rect",
        "x": 188.0,
        "y": 13.95,
        "width": 50.87,
        "height": 52.32
      },
      {
        "id": "card_t_1",
        "semantic_role": "card_value",
        "z_index": 0,
        "anchor": "middle",
        "alignment": "left",
        "fill": "#222222",
        "font_family": "Malgun Gothic",
        "font_size": 46,
        "font_weight": "normal",
        "type": "text",
        "text": "3",
        "x": 213.435,
        "y": 55.0
      },
      {
        "id": "card_2",
        "semantic_role": "card",
        "z_index": 0,
        "anchor": "start",
        "alignment": "left",
        "stroke": "#000000",
        "stroke_width": 1,
        "fill": "#BDBDBD",
        "font_family": "Malgun Gothic",
        "font_weight": "normal",
        "type": "rect",
        "x": 256.5,
        "y": 13.95,
        "width": 49.65,
        "height": 53.54
      },
      {
        "id": "card_t_2",
        "semantic_role": "card_value",
        "z_index": 0,
        "anchor": "middle",
        "alignment": "left",
        "fill": "#222222",
        "font_family": "Malgun Gothic",
        "font_size": 46,
        "font_weight": "normal",
        "type": "text",
        "text": "5",
        "x": 281.325,
        "y": 55.0
      },
      {
        "id": "card_3",
        "semantic_role": "card",
        "z_index": 0,
        "anchor": "start",
        "alignment": "left",
        "stroke": "#000000",
        "stroke_width": 1,
        "fill": "#BDBDBD",
        "font_family": "Malgun Gothic",
        "font_weight": "normal",
        "type": "rect",
        "x": 322.5,
        "y": 13.97,
        "width": 52.06,
        "height": 54.73
      },
      {
        "id": "card_t_3",
        "semantic_role": "card_value",
        "z_index": 0,
        "anchor": "middle",
        "alignment": "left",
        "fill": "#222222",
        "font_family": "Malgun Gothic",
        "font_size": 46,
        "font_weight": "normal",
        "type": "text",
        "text": "7",
        "x": 348.53,
        "y": 55.0
      },
      {
        "id": "card_4",
        "semantic_role": "card",
        "z_index": 0,
        "anchor": "start",
        "alignment": "left",
        "stroke": "#000000",
        "stroke_width": 1,
        "fill": "#BDBDBD",
        "font_family": "Malgun Gothic",
        "font_weight": "normal",
        "type": "rect",
        "x": 389.8,
        "y": 13.98,
        "width": 52.05,
        "height": 55.94
      },
      {
        "id": "card_t_4",
        "semantic_role": "card_value",
        "z_index": 0,
        "anchor": "middle",
        "alignment": "left",
        "fill": "#222222",
        "font_family": "Malgun Gothic",
        "font_size": 46,
        "font_weight": "normal",
        "type": "text",
        "text": "9",
        "x": 415.825,
        "y": 55.0
      },
      {
        "id": "l1b",
        "semantic_role": "instruction",
        "z_index": 0,
        "anchor": "start",
        "alignment": "left",
        "fill": "#222222",
        "font_family": "Malgun Gothic",
        "font_size": 33,
        "font_weight": "normal",
        "type": "text",
        "text": "를 모두 한 번씩만 사용하여",
        "x": 458.35,
        "y": 54.1
      },
      {
        "id": "l2",
        "semantic_role": "instruction",
        "z_index": 0,
        "anchor": "start",
        "alignment": "left",
        "fill": "#222222",
        "font_family": "Malgun Gothic",
        "font_size": 32,
        "font_weight": "normal",
        "type": "text",
        "text": "다음과 같이 (대분수) ÷ (자연수)를 만들려고 합니다.",
        "x": 21.72,
        "y": 114.22
      },
      {
        "id": "l3",
        "semantic_role": "instruction",
        "z_index": 0,
        "anchor": "start",
        "alignment": "left",
        "fill": "#222222",
        "font_family": "Malgun Gothic",
        "font_size": 32,
        "font_weight": "normal",
        "type": "text",
        "text": "만들 수 있는 값 중 몫이 가장 작을 때의 몫과 몫이",
        "x": 19.62,
        "y": 164.03
      },
      {
        "id": "l4",
        "semantic_role": "instruction",
        "z_index": 0,
        "anchor": "start",
        "alignment": "left",
        "fill": "#222222",
        "font_family": "Malgun Gothic",
        "font_size": 33,
        "font_weight": "normal",
        "type": "text",
        "text": "가장 클 때의 몫 사이에 있는 자연수는 모두 몇 개인가요?",
        "x": 18.35,
        "y": 215.79
      },
      {
        "id": "expr_box",
        "semantic_role": "expression",
        "z_index": 0,
        "anchor": "start",
        "alignment": "left",
        "stroke": "#000000",
        "stroke_width": 1,
        "fill": "none",
        "font_family": "Malgun Gothic",
        "font_weight": "normal",
        "type": "rect",
        "x": 268.99,
        "y": 308.46,
        "width": 315.14,
        "height": 160.19,
        "rx": 14
      },
      {
        "id": "whole_blank",
        "semantic_role": "answer_blank",
        "z_index": 0,
        "anchor": "start",
        "alignment": "left",
        "stroke": "#000000",
        "stroke_width": 1,
        "fill": "none",
        "font_family": "Malgun Gothic",
        "font_weight": "normal",
        "type": "rect",
        "x": 321.11,
        "y": 373.79,
        "width": 36.0,
        "height": 34.0
      },
      {
        "id": "frac_num_blank",
        "semantic_role": "answer_blank",
        "z_index": 0,
        "anchor": "start",
        "alignment": "left",
        "stroke": "#000000",
        "stroke_width": 1,
        "fill": "none",
        "font_family": "Malgun Gothic",
        "font_weight": "normal",
        "type": "rect",
        "x": 383.11,
        "y": 343.79,
        "width": 36.0,
        "height": 34.0
      },
      {
        "id": "frac_den_blank",
        "semantic_role": "answer_blank",
        "z_index": 0,
        "anchor": "start",
        "alignment": "left",
        "stroke": "#000000",
        "stroke_width": 1,
        "fill": "none",
        "font_family": "Malgun Gothic",
        "font_weight": "normal",
        "type": "rect",
        "x": 383.11,
        "y": 405.79,
        "width": 36.0,
        "height": 34.0
      },
      {
        "id": "frac_bar",
        "semantic_role": "operator",
        "z_index": 0,
        "anchor": "start",
        "alignment": "left",
        "stroke": "#222222",
        "stroke_width": 2,
        "font_family": "Malgun Gothic",
        "font_weight": "normal",
        "type": "line",
        "x1": 369.11,
        "y1": 390.79,
        "x2": 433.11,
        "y2": 390.79
      },
      {
        "id": "div_sign",
        "semantic_role": "operator",
        "z_index": 0,
        "anchor": "middle",
        "alignment": "left",
        "fill": "#222222",
        "font_family": "Malgun Gothic",
        "font_size": 64,
        "font_weight": "normal",
        "type": "text",
        "text": "÷",
        "x": 457.11,
        "y": 406.79
      },
      {
        "id": "div_blank",
        "semantic_role": "answer_blank",
        "z_index": 0,
        "anchor": "start",
        "alignment": "left",
        "stroke": "#000000",
        "stroke_width": 1,
        "fill": "none",
        "font_family": "Malgun Gothic",
        "font_weight": "normal",
        "type": "rect",
        "x": 486.11,
        "y": 373.79,
        "width": 36.0,
        "height": 34.0
      }
    ]
  },
  "answer": {
    "blanks": [
      {
        "id": "value",
        "kind": "numeric",
        "value": "3"
      }
    ],
    "choices": [],
    "answer_key": [
      {
        "target": "value",
        "value": "3"
      }
    ]
  }
}